{
  "match_id": "2038971",
  "fetch_time": "2026-04-21 16:29:56",
  "match_info": {
    "home_team": "拉瓦勒",
    "away_team": "兰斯",
    "league": "法国乙级联赛",
    "time": ""
  },
  "score_odds": {
    "05:00": "700.0",
    "01:00": "11.00",
    "05:02": "600.0",
    "05:01": "600.0",
    "02:04": "60.00",
    "02:05": "150.0",
    "02:02": "16.00",
    "02:03": "27.00",
    "02:00": "25.00",
    "02:01": "14.00",
    "03:03": "80.00",
    "03:01": "50.00",
    "03:02": "55.00",
    "03:00": "80.00",
    "00:01": "5.75",
    "00:00": "10.00",
    "00:03": "12.00",
    "00:02": "7.00",
    "00:05": "80.00",
    "00:04": "30.00",
    "04:02": "200.0",
    "04:01": "200.0",
    "04:00": "300.0",
    "01:02": "6.75",
    "01:01": "6.50",
    "01:04": "28.00",
    "01:03": "12.00",
    "01:05": "80.00"
  },
  "total_goals": {
    "3球": "3.60",
    "4球": "6.00",
    "5球": "12.50",
    "6球": "22.00",
    "7球": "35.00",
    "0球": "10.00",
    "1球": "4.20",
    "2球": "3.15"
  },
  "had": {
    "胜": "4.50",
    "平": "3.40",
    "负": "1.63"
  },
  "ttg": {
    "3球": "3.60",
    "4球": "6.00",
    "5球": "12.50",
    "6球": "22.00",
    "7球": "35.00",
    "0球": "10.00",
    "1球": "4.20",
    "2球": "3.15"
  },
  "hafu": {
    "负负": "2.50",
    "平平": "5.00",
    "胜胜": "8.25",
    "负平": "17.00",
    "平胜": "10.00",
    "负胜": "50.00",
    "胜负": "26.00",
    "胜平": "17.00",
    "平负": "3.90"
  },
  "hhad": {
    "让球": "+1",
    "让胜": "1.96",
    "让平": "3.10",
    "让负": "3.38"
  },
  "preview": {
    "feature": {
      "awayTeamId": 0,
      "awayTeamShortName": "兰斯",
      "eachHomeAway": {
        "awayDrawMatchCnt": 6,
        "awayLossGoalMatchCnt": 2,
        "awayScoreRatio": "40",
        "awayWinGoalMatchCnt": 2,
        "homeDrawMatchCnt": 5,
        "homeLossGoalMatchCnt": 4,
        "homeScoreRatio": "27",
        "homeWinGoalMatchCnt": 1,
        "totalLegCnt": 10
      },
      "eachSameHomeAway": {
        "awayDrawMatchCnt": 5,
        "awayLossGoalMatchCnt": 2,
        "awayScoreRatio": "47",
        "awayWinGoalMatchCnt": 3,
        "homeDrawMatchCnt": 4,
        "homeLossGoalMatchCnt": 4,
        "homeScoreRatio": "33",
        "homeWinGoalMatchCnt": 2,
        "totalLegCnt": 10
      },
      "goalAvg": {
        "awayGoalAvgCnt": "0.8",
        "awayGoalAvgCntRatio": "44.4",
        "homeGoalAvgCnt": "1.0",
        "homeGoalAvgCntRatio": "55.6",
        "totalLegCnt": 10
      },
      "homeTeamId": 0,
      "homeTeamShortName": "拉瓦勒",
      "last": {
        "awayDrawMatchCnt": 2,
        "awayLossGoalMatchCnt": 3,
        "awayScoreRatio": "38",
        "awayWinGoalMatchCnt": 2,
        "homeDrawMatchCnt": 2,
        "homeLossGoalMatchCnt": 2,
        "homeScoreRatio": "52",
        "homeWinGoalMatchCnt": 3,
        "totalLegCnt": 7
      },
      "lossGoalAvg": {
        "awayLossGoalAvgCnt": "0.5",
        "awayLossGoalAvgCntRatio": "25.0",
        "homeLossGoalAvgCnt": "1.5",
        "homeLossGoalAvgCntRatio": "75.0",
        "totalLegCnt": 10
      },
      "matchId": 2355892,
      "sameHomeAway": {
        "awayDrawMatchCnt": 0,
        "awayLossGoalMatchCnt": 2,
        "awayScoreRatio": "33",
        "awayWinGoalMatchCnt": 1,
        "homeDrawMatchCnt": 0,
        "homeLossGoalMatchCnt": 1,
        "homeScoreRatio": "67",
        "homeWinGoalMatchCnt": 2,
        "totalLegCnt": 3
      },
      "sportteryAwayTeamId": 209,
      "sportteryHomeTeamId": 201,
      "sportteryMatchId": 2038971,
      "uniformAwayTeamId": 148,
      "uniformHomeTeamId": 1245
    },
    "history": {
      "matchList": [
        {
          "awayTeamFullCourtGoalCnt": "0",
          "awayTeamId": 920,
          "awayTeamShortName": "拉瓦勒",
          "fullCourtGoal": "4:0",
          "gmLeagueId": 81,
          "halfTimeGoal": "3:0",
          "homeMatchResult": "away",
          "homeTeamFullCourtGoalCnt": "4",
          "homeTeamId": 921,
          "homeTeamShortName": "兰斯",
          "matchDate": "2025-12-09",
          "matchId": 2356027,
          "seasonId": 13417,
          "sportteryAwayTeamId": 201,
          "sportteryHomeTeamId": 209,
          "sportteryMatchId": 2035836,
          "sportteryTournamentId": 81,
          "teamMatchResult": "",
          "totalTeamFullCourtGoalCnt": 4,
          "tournamentId": 250,
          "tournamentShortName": "法乙",
          "uniformAwayTeamId": 1245,
          "uniformHomeTeamId": 148,
          "uniformLeagueId": 1049,
          "winningTeam": "home"
        },
        {
          "awayTeamFullCourtGoalCnt": "2",
          "awayTeamId": 921,
          "awayTeamShortName": "兰斯",
          "fullCourtGoal": "5:2",
          "gmLeagueId": 81,
          "halfTimeGoal": "1:2",
          "homeMatchResult": "home",
          "homeTeamFullCourtGoalCnt": "5",
          "homeTeamId": 920,
          "homeTeamShortName": "拉瓦勒",
          "matchDate": "2017-04-15",
          "matchId": 476353,
          "seasonId": 2457,
          "sportteryAwayTeamId": 209,
          "sportteryHomeTeamId": 201,
          "sportteryMatchId": 92926,
          "sportteryTournamentId": 81,
          "teamMatchResult": "",
          "totalTeamFullCourtGoalCnt": 7,
          "tournamentId": 250,
          "tournamentShortName": "法乙",
          "uniformAwayTeamId": 148,
          "uniformHomeTeamId": 1245,
          "uniformLeagueId": 1049,
          "winningTeam": "home"
        },
        {
          "awayTeamFullCourtGoalCnt": "2",
          "awayTeamId": 920,
          "awayTeamShortName": "拉瓦勒",
          "fullCourtGoal": "0:2",
          "gmLeagueId": 81,
          "halfTimeGoal": "0:1",
          "homeMatchResult": "home",
          "homeTeamFullCourtGoalCnt": "0",
          "homeTeamId": 921,
          "homeTeamShortName": "兰斯",
          "matchDate": "2016-11-19",
          "matchId": 476177,
          "seasonId": 2457,
          "sportteryAwayTeamId": 201,
          "sportteryHomeTeamId": 209,
          "sportteryMatchId": 87167,
          "sportteryTournamentId": 81,
          "teamMatchResult": "",
          "totalTeamFullCourtGoalCnt": 2,
          "tournamentId": 250,
          "tournamentShortName": "法乙",
          "uniformAwayTeamId": 1245,
          "uniformHomeTeamId": 148,
          "uniformLeagueId": 1049,
          "winningTeam": "away"
        },
        {
          "awayTeamFullCourtGoalCnt": "1",
          "awayTeamId": 920,
          "awayTeamShortName": "拉瓦勒",
          "fullCourtGoal": "1:1",
          "gmLeagueId": 81,
          "halfTimeGoal": "1:0",
          "homeMatchResult": "draw",
          "homeTeamFullCourtGoalCnt": "1",
          "homeTeamId": 921,
          "homeTeamShortName": "兰斯",
          "matchDate": "2012-03-14",
          "matchId": 15270,
          "seasonId": 52,
          "sportteryAwayTeamId": 201,
          "sportteryHomeTeamId": 209,
          "sportteryMatchId": 29293,
          "sportteryTournamentId": 81,
          "teamMatchResult": "",
          "totalTeamFullCourtGoalCnt": 2,
          "tournamentId": 250,
          "tournamentShortName": "法乙",
          "uniformAwayTeamId": 1245,
          "uniformHomeTeamId": 148,
          "uniformLeagueId": 1049,
          "winningTeam": "draw"
        },
        {
          "awayTeamFullCourtGoalCnt": "2",
          "awayTeamId": 921,
          "awayTeamShortName": "兰斯",
          "fullCourtGoal": "3:2",
          "gmLeagueId": 81,
          "halfTimeGoal": "0:1",
          "homeMatchResult": "home",
          "homeTeamFullCourtGoalCnt": "3",
          "homeTeamId": 920,
          "homeTeamShortName": "拉瓦勒",
          "matchDate": "2011-09-17",
          "matchId": 15108,
          "seasonId": 52,
          "sportteryAwayTeamId": 209,
          "sportteryHomeTeamId": 201,
          "sportteryMatchId": 23568,
          "sportteryTournamentId": 81,
          "teamMatchResult": "",
          "totalTeamFullCourtGoalCnt": 5,
          "tournamentId": 250,
          "tournamentShortName": "法乙",
          "uniformAwayTeamId": 148,
          "uniformHomeTeamId": 1245,
          "uniformLeagueId": 1049,
          "winningTeam": "home"
        }
      ],
      "statistics": {
        "drawMatchCnt": 1,
        "drawProbability": "20%",
        "goalCnt": 0,
        "lossGoalCnt": 0,
        "lossGoalMatchCnt": 1,
        "lossProbability": "20%",
        "netGoal": 0,
        "sportteryTeamId": 0,
        "teamId": 0,
        "teamShortName": "拉瓦勒",
        "totalLegCnt": 5,
        "winGoalMatchCnt": 3,
        "winProbability": "60%"
      }
    },
    "injury": {
      "away": {
        "injuriesAndSuspensionsList": [
          {
            "appearanceCnt": 12,
            "injuryFlag": 1,
            "personId": 557939,
            "personName": "M. Daramy",
            "playerPositionCode": "Forward",
            "playerPositionDesc": "前锋",
            "startedMatchCnt": 6,
            "substituteMatchCnt": 6,
            "suspensionFlag": 0,
            "uniformNo": "9"
          },
          {
            "appearanceCnt": 7,
            "injuryFlag": 1,
            "personId": 695566,
            "personName": "Y. Fofana",
            "playerPositionCode": "Midfielder",
            "playerPositionDesc": "中场",
            "startedMatchCnt": 0,
            "substituteMatchCnt": 7,
            "suspensionFlag": 0,
            "uniformNo": "8"
          }
        ],
        "sportteryTeamId": 209,
        "teamId": 921,
        "teamShortName": "兰斯",
        "uniformTeamId": 148
      },
      "home": {
        "injuriesAndSuspensionsList": [],
        "sportteryTeamId": 201,
        "teamId": 920,
        "teamShortName": "拉瓦勒",
        "uniformTeamId": 1245
      }
    },
    "recent": {
      "away": {
        "matchList": [
          {
            "awayTeamFullCourtGoalCnt": "0",
            "awayTeamId": 472,
            "awayTeamShortName": "布洛涅",
            "fullCourtGoal": "0:0",
            "halfTimeGoal": "0:0",
            "homeMatchResult": "",
            "homeTeamFullCourtGoalCnt": "0",
            "homeTeamId": 209,
            "homeTeamShortName": "兰斯",
            "matchDate": "2026-04-04",
            "matchId": 2355990,
            "seasonId": 13417,
            "sportteryAwayTeamId": 0,
            "sportteryHomeTeamId": 0,
            "sportteryMatchId": 0,
            "sportteryTournamentId": 0,
            "teamMatchResult": "draw",
            "totalTeamFullCourtGoalCnt": 0,
            "tournamentId": 250,
            "tournamentShortName": "法乙",
            "uniformAwayTeamId": 1582,
            "uniformHomeTeamId": 148,
            "uniformLeagueId": 1049,
            "winningTeam": "draw"
          },
          {
            "awayTeamFullCourtGoalCnt": "2",
            "awayTeamId": 209,
            "awayTeamShortName": "兰斯",
            "fullCourtGoal": "0:2",
            "halfTimeGoal": "0:1",
            "homeMatchResult": "",
            "homeTeamFullCourtGoalCnt": "0",
            "homeTeamId": 200,
            "homeTeamShortName": "甘冈",
            "matchDate": "2026-03-21",
            "matchId": 2355898,
            "seasonId": 13417,
            "sportteryAwayTeamId": 0,
            "sportteryHomeTeamId": 0,
            "sportteryMatchId": 0,
            "sportteryTournamentId": 0,
            "teamMatchResult": "home",
            "totalTeamFullCourtGoalCnt": 0,
            "tournamentId": 250,
            "tournamentShortName": "法乙",
            "uniformAwayTeamId": 148,
            "uniformHomeTeamId": 350,
            "uniformLeagueId": 1049,
            "winningTeam": ""
          },
          {
            "awayTeamFullCourtGoalCnt": "2",
            "awayTeamId": 476,
            "awayTeamShortName": "罗德兹",
            "fullCourtGoal": "1:2",
            "halfTimeGoal": "1:0",
            "homeMatchResult": "",
            "homeTeamFullCourtGoalCnt": "1",
            "homeTeamId": 209,
            "homeTeamShortName": "兰斯",
            "matchDate": "2026-03-14",
            "matchId": 2355995,
            "seasonId": 13417,
            "sportteryAwayTeamId": 0,
            "sportteryHomeTeamId": 0,
            "sportteryMatchId": 0,
            "sportteryTournamentId": 0,
            "teamMatchResult": "away",
            "totalTeamFullCourtGoalCnt": 0,
            "tournamentId": 250,
            "tournamentShortName": "法乙",
            "uniformAwayTeamId": 275,
            "uniformHomeTeamId": 148,
            "uniformLeagueId": 1049,
            "winningTeam": ""
          },
          {
            "awayTeamFullCourtGoalCnt": "1",
            "awayTeamId": 209,
            "awayTeamShortName": "兰斯",
            "fullCourtGoal": "1:1",
            "halfTimeGoal": "1:0",
            "homeMatchResult": "",
            "homeTeamFullCourtGoalCnt": "1",
            "homeTeamId": 1190,
            "homeTeamShortName": "敦刻尔克",
            "matchDate": "2026-03-10",
            "matchId": 2355903,
            "seasonId": 13417,
            "sportteryAwayTeamId": 0,
            "sportteryHomeTeamId": 0,
            "sportteryMatchId": 2038182,
            "sportteryTournamentId": 81,
            "teamMatchResult": "draw",
            "totalTeamFullCourtGoalCnt": 0,
            "tournamentId": 250,
            "tournamentShortName": "法乙",
            "uniformAwayTeamId": 148,
            "uniformHomeTeamId": 165,
            "uniformLeagueId": 1049,
            "winningTeam": "draw"
          },
          {
            "awayTeamFullCourtGoalCnt": "1",
            "awayTeamId": 209,
            "awayTeamShortName": "兰斯",
            "fullCourtGoal": "2:1",
            "halfTimeGoal": "0:0",
            "homeMatchResult": "",
            "homeTeamFullCourtGoalCnt": "2",
            "homeTeamId": 191,
            "homeTeamShortName": "斯特拉斯",
            "matchDate": "2026-03-04",
            "matchId": 2496778,
            "seasonId": 14102,
            "sportteryAwayTeamId": 0,
            "sportteryHomeTeamId": 0,
            "sportteryMatchId": 2038039,
            "sportteryTournamentId": 30,
            "teamMatchResult": "away",
            "totalTeamFullCourtGoalCnt": 0,
            "tournamentId": 754,
            "tournamentShortName": "法国杯",
            "uniformAwayTeamId": 148,
            "uniformHomeTeamId": 102,
            "uniformLeagueId": 18,
            "winningTeam": "home"
          }
        ],
        "statistics": {
          "drawMatchCnt": 2,
          "drawProbability": "40%",
          "goalCnt": 5,
          "lossGoalCnt": 5,
          "lossGoalMatchCnt": 2,
          "lossProbability": "40%",
          "netGoal": 0,
          "sportteryTeamId": 0,
          "teamId": 209,
          "teamShortName": "兰斯",
          "totalLegCnt": 5,
          "uniformTeamId": 148,
          "winGoalMatchCnt": 1,
          "winProbability": "20%"
        }
      },
      "home": {
        "matchList": [
          {
            "awayTeamFullCourtGoalCnt": "0",
            "awayTeamId": 201,
            "awayTeamShortName": "拉瓦勒",
            "fullCourtGoal": "0:0",
            "halfTimeGoal": "0:0",
            "homeMatchResult": "",
            "homeTeamFullCourtGoalCnt": "0",
            "homeTeamId": 1643,
            "homeTeamShortName": "圣旺红星",
            "matchDate": "2026-04-04",
            "matchId": 2355991,
            "seasonId": 13417,
            "sportteryAwayTeamId": 0,
            "sportteryHomeTeamId": 0,
            "sportteryMatchId": 2038789,
            "sportteryTournamentId": 81,
            "teamMatchResult": "draw",
            "totalTeamFullCourtGoalCnt": 0,
            "tournamentId": 250,
            "tournamentShortName": "法乙",
            "uniformAwayTeamId": 1245,
            "uniformHomeTeamId": 346,
            "uniformLeagueId": 1049,
            "winningTeam": "draw"
          },
          {
            "awayTeamFullCourtGoalCnt": "2",
            "awayTeamId": 451,
            "awayTeamShortName": "格勒诺布",
            "fullCourtGoal": "3:2",
            "halfTimeGoal": "0:1",
            "homeMatchResult": "",
            "homeTeamFullCourtGoalCnt": "3",
            "homeTeamId": 201,
            "homeTeamShortName": "拉瓦勒",
            "matchDate": "2026-03-21",
            "matchId": 2355897,
            "seasonId": 13417,
            "sportteryAwayTeamId": 0,
            "sportteryHomeTeamId": 0,
            "sportteryMatchId": 0,
            "sportteryTournamentId": 0,
            "teamMatchResult": "home",
            "totalTeamFullCourtGoalCnt": 0,
            "tournamentId": 250,
            "tournamentShortName": "法乙",
            "uniformAwayTeamId": 499,
            "uniformHomeTeamId": 1245,
            "uniformLeagueId": 1049,
            "winningTeam": "home"
          },
          {
            "awayTeamFullCourtGoalCnt": "0",
            "awayTeamId": 201,
            "awayTeamShortName": "拉瓦勒",
            "fullCourtGoal": "2:0",
            "halfTimeGoal": "0:0",
            "homeMatchResult": "",
            "homeTeamFullCourtGoalCnt": "2",
            "homeTeamId": 197,
            "homeTeamShortName": "蒙彼利埃",
            "matchDate": "2026-03-14",
            "matchId": 2355994,
            "seasonId": 13417,
            "sportteryAwayTeamId": 0,
            "sportteryHomeTeamId": 0,
            "sportteryMatchId": 0,
            "sportteryTournamentId": 0,
            "teamMatchResult": "away",
            "totalTeamFullCourtGoalCnt": 0,
            "tournamentId": 250,
            "tournamentShortName": "法乙",
            "uniformAwayTeamId": 1245,
            "uniformHomeTeamId": 537,
            "uniformLeagueId": 1049,
            "winningTeam": "home"
          },
          {
            "awayTeamFullCourtGoalCnt": "2",
            "awayTeamId": 200,
            "awayTeamShortName": "甘冈",
            "fullCourtGoal": "2:2",
            "halfTimeGoal": "1:0",
            "homeMatchResult": "",
            "homeTeamFullCourtGoalCnt": "2",
            "homeTeamId": 201,
            "homeTeamShortName": "拉瓦勒",
            "matchDate": "2026-03-07",
            "matchId": 2355902,
            "seasonId": 13417,
            "sportteryAwayTeamId": 0,
            "sportteryHomeTeamId": 0,
            "sportteryMatchId": 0,
            "sportteryTournamentId": 0,
            "teamMatchResult": "draw",
            "totalTeamFullCourtGoalCnt": 0,
            "tournamentId": 250,
            "tournamentShortName": "法乙",
            "uniformAwayTeamId": 350,
            "uniformHomeTeamId": 1245,
            "uniformLeagueId": 1049,
            "winningTeam": "draw"
          },
          {
            "awayTeamFullCourtGoalCnt": "1",
            "awayTeamId": 450,
            "awayTeamShortName": "南锡",
            "fullCourtGoal": "1:1",
            "halfTimeGoal": "1:0",
            "homeMatchResult": "",
            "homeTeamFullCourtGoalCnt": "1",
            "homeTeamId": 201,
            "homeTeamShortName": "拉瓦勒",
            "matchDate": "2026-02-28",
            "matchId": 2355905,
            "seasonId": 13417,
            "sportteryAwayTeamId": 0,
            "sportteryHomeTeamId": 0,
            "sportteryMatchId": 0,
            "sportteryTournamentId": 0,
            "teamMatchResult": "draw",
            "totalTeamFullCourtGoalCnt": 0,
            "tournamentId": 250,
            "tournamentShortName": "法乙",
            "uniformAwayTeamId": 284,
            "uniformHomeTeamId": 1245,
            "uniformLeagueId": 1049,
            "winningTeam": "draw"
          }
        ],
        "statistics": {
          "drawMatchCnt": 3,
          "drawProbability": "60%",
          "goalCnt": 6,
          "lossGoalCnt": 7,
          "lossGoalMatchCnt": 1,
          "lossProbability": "20%",
          "netGoal": -1,
          "sportteryTeamId": 0,
          "teamId": 201,
          "teamShortName": "拉瓦勒",
          "totalLegCnt": 5,
          "uniformTeamId": 1245,
          "winGoalMatchCnt": 1,
          "winProbability": "20%"
        }
      }
    },
    "tables": {
      "phaseId": 47910,
      "seasonId": 13417,
      "seasonName": "2025/2026",
      "tables": [
        {
          "drawMatchCnt": 13,
          "groupId": 0,
          "groupName": "",
          "lossGoalMatchCnt": 13,
          "phaseName": "",
          "points": "25",
          "ranking": "16",
          "sportteryTeamId": 201,
          "teamId": 0,
          "teamShortName": "拉瓦勒",
          "totalLegCnt": 30,
          "uniformTeamId": 1245,
          "winGoalMatchCnt": 4,
          "winProbability": "13%"
        },
        {
          "drawMatchCnt": 12,
          "groupId": 0,
          "groupName": "",
          "lossGoalMatchCnt": 6,
          "phaseName": "",
          "points": "51",
          "ranking": "4",
          "sportteryTeamId": 209,
          "teamId": 0,
          "teamShortName": "兰斯",
          "totalLegCnt": 31,
          "uniformTeamId": 148,
          "winGoalMatchCnt": 13,
          "winProbability": "42%"
        }
      ],
      "tournamentId": 250,
      "tournamentShortName": "法乙",
      "uniformLeagueId": 1049,
      "uniformMatchId": 2385894
    },
    "player": {
      "away": {
        "playerList": [
          {
            "appearanceCnt": 26,
            "assistAvgCnt": "0.1",
            "assistCnt": 2,
            "assistProbability": "6%",
            "goalAvgCnt": "0.4",
            "goalCnt": 10,
            "goalProbability": "21%",
            "injuryFlag": 0,
            "personId": 479397,
            "personName": "K.中村",
            "playerPositionCode": "Forward",
            "playerPositionDesc": "前锋",
            "startedMatchCnt": 25,
            "substituteMatchCnt": 1,
            "suspensionFlag": 0,
            "uniformNo": "17"
          },
          {
            "appearanceCnt": 21,
            "assistAvgCnt": "0",
            "assistCnt": 1,
            "assistProbability": "3%",
            "goalAvgCnt": "0.3",
            "goalCnt": 6,
            "goalProbability": "13%",
            "injuryFlag": 0,
            "personId": 879388,
            "personName": "H. Ibrahim",
            "playerPositionCode": "Forward",
            "playerPositionDesc": "前锋",
            "startedMatchCnt": 9,
            "substituteMatchCnt": 12,
            "suspensionFlag": 0,
            "uniformNo": "85"
          },
          {
            "appearanceCnt": 29,
            "assistAvgCnt": "0",
            "assistCnt": 0,
            "assistProbability": "0%",
            "goalAvgCnt": "0.2",
            "goalCnt": 5,
            "goalProbability": "11%",
            "injuryFlag": 0,
            "personId": 789726,
            "personName": "A. Tia",
            "playerPositionCode": "Midfielder",
            "playerPositionDesc": "中场",
            "startedMatchCnt": 19,
            "substituteMatchCnt": 10,
            "suspensionFlag": 0,
            "uniformNo": "87"
          }
        ],
        "sportteryTeamId": 209,
        "teamId": 921,
        "teamShortName": "兰斯",
        "uniformTeamId": 148
      },
      "home": {
        "playerList": [
          {
            "appearanceCnt": 26,
            "assistAvgCnt": "0",
            "assistCnt": 0,
            "assistProbability": "0%",
            "goalAvgCnt": "0.3",
            "goalCnt": 8,
            "goalProbability": "28%",
            "injuryFlag": 0,
            "personId": 547047,
            "personName": "Mamadou Camara",
            "playerPositionCode": "Forward",
            "playerPositionDesc": "前锋",
            "startedMatchCnt": 23,
            "substituteMatchCnt": 3,
            "suspensionFlag": 0,
            "uniformNo": "9"
          },
          {
            "appearanceCnt": 23,
            "assistAvgCnt": "0",
            "assistCnt": 0,
            "assistProbability": "0%",
            "goalAvgCnt": "0.2",
            "goalCnt": 5,
            "goalProbability": "17%",
            "injuryFlag": 0,
            "personId": 893613,
            "personName": "E. Clavreul",
            "playerPositionCode": "Midfielder",
            "playerPositionDesc": "中场",
            "startedMatchCnt": 8,
            "substituteMatchCnt": 15,
            "suspensionFlag": 0,
            "uniformNo": "20"
          },
          {
            "appearanceCnt": 26,
            "assistAvgCnt": "0.1",
            "assistCnt": 2,
            "assistProbability": "15%",
            "goalAvgCnt": "0.2",
            "goalCnt": 4,
            "goalProbability": "14%",
            "injuryFlag": 0,
            "personId": 601547,
            "personName": "M.塞卢基",
            "playerPositionCode": "Midfielder",
            "playerPositionDesc": "中场",
            "startedMatchCnt": 20,
            "substituteMatchCnt": 6,
            "suspensionFlag": 0,
            "uniformNo": "10"
          }
        ],
        "sportteryTeamId": 201,
        "teamId": 920,
        "teamShortName": "拉瓦勒",
        "uniformTeamId": 1245
      },
      "seasonId": 13417,
      "seasonName": "2025/2026",
      "tournamentId": 250,
      "tournamentShortName": "法乙",
      "uniformLeagueId": 1049,
      "uniformMatchId": 2385894
    }
  },
  "ttg_change": {},
  "hafu_change": {},
  "exclusion_list": [
    {
      "goal": "2球",
      "ttg_odds": "3.15",
      "ttg_special": true,
      "scores": [
        {
          "score": "02:00",
          "odds": "25.00",
          "special": false
        },
        {
          "score": "00:02",
          "odds": "7.00",
          "special": false
        },
        {
          "score": "01:01",
          "odds": "6.50",
          "special": false
        }
      ],
      "level": "普通排除",
      "reason": "进球数赔率(3.15)含特殊尾数，排除该进球数及其所有比分"
    },
    {
      "goal": "1球",
      "ttg_odds": "4.20",
      "ttg_special": false,
      "scores": [
        {
          "score": "01:00",
          "odds": "11.00",
          "special": false
        },
        {
          "score": "00:01",
          "odds": "5.75",
          "special": true
        }
      ],
      "level": "仅比分排除",
      "reason": "进球数赔率4.20（普通），但对应比分中存在特殊尾数赔率，可优先排除特殊尾数比分"
    },
    {
      "goal": "3球",
      "ttg_odds": "3.60",
      "ttg_special": false,
      "scores": [
        {
          "score": "02:01",
          "odds": "14.00",
          "special": false
        },
        {
          "score": "03:00",
          "odds": "80.00",
          "special": false
        },
        {
          "score": "00:03",
          "odds": "12.00",
          "special": false
        },
        {
          "score": "01:02",
          "odds": "6.75",
          "special": true
        }
      ],
      "level": "仅比分排除",
      "reason": "进球数赔率3.60（普通），但对应比分中存在特殊尾数赔率，可优先排除特殊尾数比分"
    }
  ]
}