{
  "match_id": "2039616",
  "fetch_time": "2026-05-09 21:11:46",
  "match_info": {
    "home_team": "曼彻斯特城",
    "away_team": "布伦特福德",
    "league": "英格兰超级联赛",
    "time": "2026-05-10 00:30",
    "match_num_str": "周六023",
    "match_week": "周六",
    "match_date": "2026-05-10",
    "match_time": "00:30:00",
    "match_status": "Selling",
    "home_rank": "[英超2]",
    "away_rank": "[英超7]",
    "league_abbr": "英超"
  },
  "score_odds": {
    "05:00": "28.00",
    "01:00": "10.00",
    "05:02": "60.00",
    "05:01": "29.00",
    "02:04": "175.0",
    "02:05": "550.0",
    "02:02": "15.00",
    "02:03": "45.00",
    "02:00": "7.75",
    "02:01": "7.00",
    "03:03": "52.00",
    "03:01": "8.00",
    "03:02": "16.50",
    "03:00": "9.00",
    "00:01": "27.00",
    "00:00": "28.00",
    "00:03": "150.0",
    "00:02": "55.00",
    "00:05": "1000",
    "00:04": "550.0",
    "04:02": "29.00",
    "04:01": "13.00",
    "04:00": "14.00",
    "01:02": "19.00",
    "01:01": "11.00",
    "01:04": "200.0",
    "01:03": "60.00",
    "01:05": "650.0"
  },
  "total_goals": {
    "3球": "3.50",
    "4球": "4.05",
    "5球": "5.80",
    "6球": "9.50",
    "7球": "11.50",
    "0球": "28.00",
    "1球": "8.50",
    "2球": "4.90"
  },
  "had": {
    "胜": "1.23",
    "平": "5.50",
    "负": "7.45"
  },
  "ttg": {
    "3球": "3.50",
    "4球": "4.05",
    "5球": "5.80",
    "6球": "9.50",
    "7球": "11.50",
    "0球": "28.00",
    "1球": "8.50",
    "2球": "4.90"
  },
  "hafu": {
    "负负": "12.50",
    "平平": "9.50",
    "胜胜": "1.68",
    "负平": "19.00",
    "平胜": "4.15",
    "负胜": "20.00",
    "胜负": "55.00",
    "胜平": "19.00",
    "平负": "17.00"
  },
  "hhad": {
    "让球": "-1",
    "让胜": "1.75",
    "让平": "4.00",
    "让负": "3.25"
  },
  "preview": {
    "feature": {
      "awayTeamId": 0,
      "awayTeamShortName": "布伦特",
      "eachHomeAway": {
        "awayDrawMatchCnt": 6,
        "awayLossGoalMatchCnt": 2,
        "awayScoreRatio": "40",
        "awayWinGoalMatchCnt": 2,
        "homeDrawMatchCnt": 2,
        "homeLossGoalMatchCnt": 2,
        "homeScoreRatio": "67",
        "homeWinGoalMatchCnt": 6,
        "totalLegCnt": 10
      },
      "eachSameHomeAway": {
        "awayDrawMatchCnt": 3,
        "awayLossGoalMatchCnt": 2,
        "awayScoreRatio": "60",
        "awayWinGoalMatchCnt": 5,
        "homeDrawMatchCnt": 1,
        "homeLossGoalMatchCnt": 1,
        "homeScoreRatio": "83",
        "homeWinGoalMatchCnt": 8,
        "totalLegCnt": 10
      },
      "goalAvg": {
        "awayGoalAvgCnt": "1.4",
        "awayGoalAvgCntRatio": "42.4",
        "homeGoalAvgCnt": "1.9",
        "homeGoalAvgCntRatio": "57.6",
        "totalLegCnt": 10
      },
      "homeTeamId": 0,
      "homeTeamShortName": "曼城",
      "last": {
        "awayDrawMatchCnt": 1,
        "awayLossGoalMatchCnt": 7,
        "awayScoreRatio": "23",
        "awayWinGoalMatchCnt": 2,
        "homeDrawMatchCnt": 1,
        "homeLossGoalMatchCnt": 2,
        "homeScoreRatio": "73",
        "homeWinGoalMatchCnt": 7,
        "totalLegCnt": 10
      },
      "lossGoalAvg": {
        "awayLossGoalAvgCnt": "1.3",
        "awayLossGoalAvgCntRatio": "54.2",
        "homeLossGoalAvgCnt": "1.1",
        "homeLossGoalAvgCntRatio": "45.8",
        "totalLegCnt": 10
      },
      "matchId": 2346466,
      "sameHomeAway": {
        "awayDrawMatchCnt": 0,
        "awayLossGoalMatchCnt": 4,
        "awayScoreRatio": "20",
        "awayWinGoalMatchCnt": 1,
        "homeDrawMatchCnt": 0,
        "homeLossGoalMatchCnt": 1,
        "homeScoreRatio": "80",
        "homeWinGoalMatchCnt": 4,
        "totalLegCnt": 5
      },
      "sportteryAwayTeamId": 69,
      "sportteryHomeTeamId": 12,
      "sportteryMatchId": 2039616,
      "uniformAwayTeamId": 421,
      "uniformHomeTeamId": 217
    },
    "history": {
      "matchList": [
        {
          "awayTeamFullCourtGoalCnt": "0",
          "awayTeamId": 722,
          "awayTeamShortName": "布伦特",
          "fullCourtGoal": "2:0",
          "gmLeagueId": 24,
          "halfTimeGoal": "1:0",
          "homeMatchResult": "home",
          "homeTeamFullCourtGoalCnt": "2",
          "homeTeamId": 676,
          "homeTeamShortName": "曼城",
          "matchDate": "2025-12-18",
          "matchId": 2457254,
          "seasonId": 13402,
          "sportteryAwayTeamId": 69,
          "sportteryHomeTeamId": 12,
          "sportteryMatchId": 2036104,
          "sportteryTournamentId": 24,
          "teamMatchResult": "",
          "totalTeamFullCourtGoalCnt": 2,
          "tournamentId": 585,
          "tournamentShortName": "英联赛杯",
          "uniformAwayTeamId": 421,
          "uniformHomeTeamId": 217,
          "uniformLeagueId": 25,
          "winningTeam": "home"
        },
        {
          "awayTeamFullCourtGoalCnt": "1",
          "awayTeamId": 676,
          "awayTeamShortName": "曼城",
          "fullCourtGoal": "0:1",
          "gmLeagueId": 25,
          "halfTimeGoal": "0:1",
          "homeMatchResult": "home",
          "homeTeamFullCourtGoalCnt": "0",
          "homeTeamId": 722,
          "homeTeamShortName": "布伦特",
          "matchDate": "2025-10-05",
          "matchId": 2346343,
          "seasonId": 13343,
          "sportteryAwayTeamId": 12,
          "sportteryHomeTeamId": 69,
          "sportteryMatchId": 2033971,
          "sportteryTournamentId": 25,
          "teamMatchResult": "",
          "totalTeamFullCourtGoalCnt": 1,
          "tournamentId": 127,
          "tournamentShortName": "英超",
          "uniformAwayTeamId": 217,
          "uniformHomeTeamId": 421,
          "uniformLeagueId": 72,
          "winningTeam": "away"
        },
        {
          "awayTeamFullCourtGoalCnt": "2",
          "awayTeamId": 676,
          "awayTeamShortName": "曼城",
          "fullCourtGoal": "2:2",
          "gmLeagueId": 25,
          "halfTimeGoal": "0:0",
          "homeMatchResult": "draw",
          "homeTeamFullCourtGoalCnt": "2",
          "homeTeamId": 722,
          "homeTeamShortName": "布伦特",
          "matchDate": "2025-01-15",
          "matchId": 2126697,
          "seasonId": 11817,
          "sportteryAwayTeamId": 12,
          "sportteryHomeTeamId": 69,
          "sportteryMatchId": 1029431,
          "sportteryTournamentId": 25,
          "teamMatchResult": "",
          "totalTeamFullCourtGoalCnt": 4,
          "tournamentId": 127,
          "tournamentShortName": "英超",
          "uniformAwayTeamId": 217,
          "uniformHomeTeamId": 421,
          "uniformLeagueId": 72,
          "winningTeam": "draw"
        },
        {
          "awayTeamFullCourtGoalCnt": "1",
          "awayTeamId": 722,
          "awayTeamShortName": "布伦特",
          "fullCourtGoal": "2:1",
          "gmLeagueId": 25,
          "halfTimeGoal": "2:1",
          "homeMatchResult": "home",
          "homeTeamFullCourtGoalCnt": "2",
          "homeTeamId": 676,
          "homeTeamShortName": "曼城",
          "matchDate": "2024-09-14",
          "matchId": 2126492,
          "seasonId": 11817,
          "sportteryAwayTeamId": 69,
          "sportteryHomeTeamId": 12,
          "sportteryMatchId": 1026974,
          "sportteryTournamentId": 25,
          "teamMatchResult": "",
          "totalTeamFullCourtGoalCnt": 3,
          "tournamentId": 127,
          "tournamentShortName": "英超",
          "uniformAwayTeamId": 421,
          "uniformHomeTeamId": 217,
          "uniformLeagueId": 72,
          "winningTeam": "home"
        },
        {
          "awayTeamFullCourtGoalCnt": "0",
          "awayTeamId": 722,
          "awayTeamShortName": "布伦特",
          "fullCourtGoal": "1:0",
          "gmLeagueId": 25,
          "halfTimeGoal": "0:0",
          "homeMatchResult": "home",
          "homeTeamFullCourtGoalCnt": "1",
          "homeTeamId": 676,
          "homeTeamShortName": "曼城",
          "matchDate": "2024-02-21",
          "matchId": 2000850,
          "seasonId": 10906,
          "sportteryAwayTeamId": 69,
          "sportteryHomeTeamId": 12,
          "sportteryMatchId": 1023612,
          "sportteryTournamentId": 25,
          "teamMatchResult": "",
          "totalTeamFullCourtGoalCnt": 1,
          "tournamentId": 127,
          "tournamentShortName": "英超",
          "uniformAwayTeamId": 421,
          "uniformHomeTeamId": 217,
          "uniformLeagueId": 72,
          "winningTeam": "home"
        }
      ],
      "statistics": {
        "drawMatchCnt": 1,
        "drawProbability": "20%",
        "goalCnt": 0,
        "lossGoalCnt": 0,
        "lossGoalMatchCnt": 0,
        "lossProbability": "0%",
        "netGoal": 0,
        "sportteryTeamId": 0,
        "teamId": 0,
        "teamShortName": "曼城",
        "totalLegCnt": 5,
        "winGoalMatchCnt": 4,
        "winProbability": "80%"
      }
    },
    "injury": {
      "away": {
        "injuriesAndSuspensionsList": [
          {
            "appearanceCnt": 29,
            "injuryFlag": 1,
            "personId": 48010,
            "personName": "亨德森",
            "playerPositionCode": "Midfielder",
            "playerPositionDesc": "中场",
            "startedMatchCnt": 21,
            "substituteMatchCnt": 8,
            "suspensionFlag": 0,
            "uniformNo": "6"
          },
          {
            "appearanceCnt": 6,
            "injuryFlag": 1,
            "personId": 525808,
            "personName": "F.卡瓦略",
            "playerPositionCode": "Midfielder",
            "playerPositionDesc": "中场",
            "startedMatchCnt": 1,
            "substituteMatchCnt": 5,
            "suspensionFlag": 0,
            "uniformNo": "14"
          },
          {
            "appearanceCnt": 1,
            "injuryFlag": 1,
            "personId": 677624,
            "personName": "A. Milambo",
            "playerPositionCode": "Midfielder",
            "playerPositionDesc": "中场",
            "startedMatchCnt": 1,
            "substituteMatchCnt": 0,
            "suspensionFlag": 0,
            "uniformNo": "17"
          }
        ],
        "sportteryTeamId": 69,
        "teamId": 722,
        "teamShortName": "布伦特",
        "uniformTeamId": 421
      },
      "home": {
        "injuriesAndSuspensionsList": [
          {
            "appearanceCnt": 16,
            "injuryFlag": 1,
            "personId": 579285,
            "personName": "格瓦迪奥尔",
            "playerPositionCode": "Defender",
            "playerPositionDesc": "后卫",
            "startedMatchCnt": 15,
            "substituteMatchCnt": 1,
            "suspensionFlag": 0,
            "uniformNo": "24"
          },
          {
            "appearanceCnt": 0,
            "injuryFlag": 1,
            "personId": 695527,
            "personName": "J. Ndala",
            "playerPositionCode": "Attacker",
            "playerPositionDesc": "前锋",
            "startedMatchCnt": 0,
            "substituteMatchCnt": 0,
            "suspensionFlag": 0,
            "uniformNo": ""
          }
        ],
        "sportteryTeamId": 12,
        "teamId": 676,
        "teamShortName": "曼城",
        "uniformTeamId": 217
      }
    },
    "recent": {
      "away": {
        "matchList": [
          {
            "awayTeamFullCourtGoalCnt": "0",
            "awayTeamId": 62,
            "awayTeamShortName": "西汉姆联",
            "fullCourtGoal": "3:0",
            "halfTimeGoal": "1:0",
            "homeMatchResult": "",
            "homeTeamFullCourtGoalCnt": "3",
            "homeTeamId": 69,
            "homeTeamShortName": "布伦特",
            "matchDate": "2026-05-02",
            "matchId": 2346270,
            "seasonId": 13343,
            "sportteryAwayTeamId": 0,
            "sportteryHomeTeamId": 0,
            "sportteryMatchId": 2039462,
            "sportteryTournamentId": 25,
            "teamMatchResult": "home",
            "totalTeamFullCourtGoalCnt": 0,
            "tournamentId": 127,
            "tournamentShortName": "英超",
            "uniformAwayTeamId": 509,
            "uniformHomeTeamId": 421,
            "uniformLeagueId": 72,
            "winningTeam": "home"
          },
          {
            "awayTeamFullCourtGoalCnt": "1",
            "awayTeamId": 69,
            "awayTeamShortName": "布伦特",
            "fullCourtGoal": "2:1",
            "halfTimeGoal": "2:0",
            "homeMatchResult": "",
            "homeTeamFullCourtGoalCnt": "2",
            "homeTeamId": 13,
            "homeTeamShortName": "曼联",
            "matchDate": "2026-04-28",
            "matchId": 2346471,
            "seasonId": 13343,
            "sportteryAwayTeamId": 0,
            "sportteryHomeTeamId": 0,
            "sportteryMatchId": 2039372,
            "sportteryTournamentId": 25,
            "teamMatchResult": "away",
            "totalTeamFullCourtGoalCnt": 0,
            "tournamentId": 127,
            "tournamentShortName": "英超",
            "uniformAwayTeamId": 421,
            "uniformHomeTeamId": 360,
            "uniformLeagueId": 72,
            "winningTeam": "home"
          },
          {
            "awayTeamFullCourtGoalCnt": "0",
            "awayTeamId": 10,
            "awayTeamShortName": "富勒姆",
            "fullCourtGoal": "0:0",
            "halfTimeGoal": "0:0",
            "homeMatchResult": "",
            "homeTeamFullCourtGoalCnt": "0",
            "homeTeamId": 69,
            "homeTeamShortName": "布伦特",
            "matchDate": "2026-04-18",
            "matchId": 2346277,
            "seasonId": 13343,
            "sportteryAwayTeamId": 0,
            "sportteryHomeTeamId": 0,
            "sportteryMatchId": 2039158,
            "sportteryTournamentId": 25,
            "teamMatchResult": "draw",
            "totalTeamFullCourtGoalCnt": 0,
            "tournamentId": 127,
            "tournamentShortName": "英超",
            "uniformAwayTeamId": 24,
            "uniformHomeTeamId": 421,
            "uniformLeagueId": 72,
            "winningTeam": "draw"
          },
          {
            "awayTeamFullCourtGoalCnt": "2",
            "awayTeamId": 9,
            "awayTeamShortName": "埃弗顿",
            "fullCourtGoal": "2:2",
            "halfTimeGoal": "1:1",
            "homeMatchResult": "",
            "homeTeamFullCourtGoalCnt": "2",
            "homeTeamId": 69,
            "homeTeamShortName": "布伦特",
            "matchDate": "2026-04-11",
            "matchId": 2346279,
            "seasonId": 13343,
            "sportteryAwayTeamId": 0,
            "sportteryHomeTeamId": 0,
            "sportteryMatchId": 2039019,
            "sportteryTournamentId": 25,
            "teamMatchResult": "draw",
            "totalTeamFullCourtGoalCnt": 0,
            "tournamentId": 127,
            "tournamentShortName": "英超",
            "uniformAwayTeamId": 1,
            "uniformHomeTeamId": 421,
            "uniformLeagueId": 72,
            "winningTeam": "draw"
          },
          {
            "awayTeamFullCourtGoalCnt": "0",
            "awayTeamId": 69,
            "awayTeamShortName": "布伦特",
            "fullCourtGoal": "0:0",
            "halfTimeGoal": "0:0",
            "homeMatchResult": "",
            "homeTeamFullCourtGoalCnt": "0",
            "homeTeamId": 49,
            "homeTeamShortName": "利兹联",
            "matchDate": "2026-03-22",
            "matchId": 2346379,
            "seasonId": 13343,
            "sportteryAwayTeamId": 0,
            "sportteryHomeTeamId": 0,
            "sportteryMatchId": 2038526,
            "sportteryTournamentId": 25,
            "teamMatchResult": "draw",
            "totalTeamFullCourtGoalCnt": 0,
            "tournamentId": 127,
            "tournamentShortName": "英超",
            "uniformAwayTeamId": 421,
            "uniformHomeTeamId": 448,
            "uniformLeagueId": 72,
            "winningTeam": "draw"
          }
        ],
        "statistics": {
          "drawMatchCnt": 3,
          "drawProbability": "60%",
          "goalCnt": 6,
          "lossGoalCnt": 4,
          "lossGoalMatchCnt": 1,
          "lossProbability": "20%",
          "netGoal": 2,
          "sportteryTeamId": 0,
          "teamId": 69,
          "teamShortName": "布伦特",
          "totalLegCnt": 5,
          "uniformTeamId": 421,
          "winGoalMatchCnt": 1,
          "winProbability": "20%"
        }
      },
      "home": {
        "matchList": [
          {
            "awayTeamFullCourtGoalCnt": "3",
            "awayTeamId": 12,
            "awayTeamShortName": "曼城",
            "fullCourtGoal": "3:3",
            "halfTimeGoal": "0:1",
            "homeMatchResult": "",
            "homeTeamFullCourtGoalCnt": "3",
            "homeTeamId": 9,
            "homeTeamShortName": "埃弗顿",
            "matchDate": "2026-05-05",
            "matchId": 2346369,
            "seasonId": 13343,
            "sportteryAwayTeamId": 0,
            "sportteryHomeTeamId": 0,
            "sportteryMatchId": 2039515,
            "sportteryTournamentId": 25,
            "teamMatchResult": "draw",
            "totalTeamFullCourtGoalCnt": 0,
            "tournamentId": 127,
            "tournamentShortName": "英超",
            "uniformAwayTeamId": 217,
            "uniformHomeTeamId": 1,
            "uniformLeagueId": 72,
            "winningTeam": "draw"
          },
          {
            "awayTeamFullCourtGoalCnt": "1",
            "awayTeamId": 18,
            "awayTeamShortName": "南安普敦",
            "fullCourtGoal": "2:1",
            "halfTimeGoal": "0:0",
            "homeMatchResult": "",
            "homeTeamFullCourtGoalCnt": "2",
            "homeTeamId": 12,
            "homeTeamShortName": "曼城",
            "matchDate": "2026-04-26",
            "matchId": 2516749,
            "seasonId": 13475,
            "sportteryAwayTeamId": 0,
            "sportteryHomeTeamId": 0,
            "sportteryMatchId": 2039328,
            "sportteryTournamentId": 23,
            "teamMatchResult": "home",
            "totalTeamFullCourtGoalCnt": 0,
            "tournamentId": 571,
            "tournamentShortName": "英足总杯",
            "uniformAwayTeamId": 358,
            "uniformHomeTeamId": 217,
            "uniformLeagueId": 17,
            "winningTeam": "home"
          },
          {
            "awayTeamFullCourtGoalCnt": "1",
            "awayTeamId": 12,
            "awayTeamShortName": "曼城",
            "fullCourtGoal": "0:1",
            "halfTimeGoal": "0:1",
            "homeMatchResult": "",
            "homeTeamFullCourtGoalCnt": "0",
            "homeTeamId": 42,
            "homeTeamShortName": "伯恩利",
            "matchDate": "2026-04-23",
            "matchId": 2346372,
            "seasonId": 13343,
            "sportteryAwayTeamId": 0,
            "sportteryHomeTeamId": 0,
            "sportteryMatchId": 2039260,
            "sportteryTournamentId": 25,
            "teamMatchResult": "home",
            "totalTeamFullCourtGoalCnt": 0,
            "tournamentId": 127,
            "tournamentShortName": "英超",
            "uniformAwayTeamId": 217,
            "uniformHomeTeamId": 203,
            "uniformLeagueId": 72,
            "winningTeam": ""
          },
          {
            "awayTeamFullCourtGoalCnt": "1",
            "awayTeamId": 1,
            "awayTeamShortName": "阿森纳",
            "fullCourtGoal": "2:1",
            "halfTimeGoal": "1:1",
            "homeMatchResult": "",
            "homeTeamFullCourtGoalCnt": "2",
            "homeTeamId": 12,
            "homeTeamShortName": "曼城",
            "matchDate": "2026-04-19",
            "matchId": 2346474,
            "seasonId": 13343,
            "sportteryAwayTeamId": 0,
            "sportteryHomeTeamId": 0,
            "sportteryMatchId": 2039197,
            "sportteryTournamentId": 25,
            "teamMatchResult": "home",
            "totalTeamFullCourtGoalCnt": 0,
            "tournamentId": 127,
            "tournamentShortName": "英超",
            "uniformAwayTeamId": 1193,
            "uniformHomeTeamId": 217,
            "uniformLeagueId": 72,
            "winningTeam": "home"
          },
          {
            "awayTeamFullCourtGoalCnt": "3",
            "awayTeamId": 12,
            "awayTeamShortName": "曼城",
            "fullCourtGoal": "0:3",
            "halfTimeGoal": "0:0",
            "homeMatchResult": "",
            "homeTeamFullCourtGoalCnt": "0",
            "homeTeamId": 7,
            "homeTeamShortName": "切尔西",
            "matchDate": "2026-04-12",
            "matchId": 2346377,
            "seasonId": 13343,
            "sportteryAwayTeamId": 0,
            "sportteryHomeTeamId": 0,
            "sportteryMatchId": 2039053,
            "sportteryTournamentId": 25,
            "teamMatchResult": "home",
            "totalTeamFullCourtGoalCnt": 0,
            "tournamentId": 127,
            "tournamentShortName": "英超",
            "uniformAwayTeamId": 217,
            "uniformHomeTeamId": 2,
            "uniformLeagueId": 72,
            "winningTeam": ""
          }
        ],
        "statistics": {
          "drawMatchCnt": 1,
          "drawProbability": "20%",
          "goalCnt": 11,
          "lossGoalCnt": 5,
          "lossGoalMatchCnt": 0,
          "lossProbability": "0%",
          "netGoal": 6,
          "sportteryTeamId": 0,
          "teamId": 12,
          "teamShortName": "曼城",
          "totalLegCnt": 5,
          "uniformTeamId": 217,
          "winGoalMatchCnt": 4,
          "winProbability": "80%"
        }
      }
    },
    "tables": {
      "phaseId": 47855,
      "seasonId": 13343,
      "seasonName": "2025/2026",
      "tables": [
        {
          "drawMatchCnt": 8,
          "groupId": 0,
          "groupName": "",
          "lossGoalMatchCnt": 5,
          "phaseName": "",
          "points": "71",
          "ranking": "2",
          "sportteryTeamId": 12,
          "teamId": 0,
          "teamShortName": "曼城",
          "totalLegCnt": 34,
          "uniformTeamId": 217,
          "winGoalMatchCnt": 21,
          "winProbability": "62%"
        },
        {
          "drawMatchCnt": 9,
          "groupId": 0,
          "groupName": "",
          "lossGoalMatchCnt": 12,
          "phaseName": "",
          "points": "51",
          "ranking": "7",
          "sportteryTeamId": 69,
          "teamId": 0,
          "teamShortName": "布伦特",
          "totalLegCnt": 35,
          "uniformTeamId": 421,
          "winGoalMatchCnt": 14,
          "winProbability": "40%"
        }
      ],
      "tournamentId": 127,
      "tournamentShortName": "英超",
      "uniformLeagueId": 72,
      "uniformMatchId": 2390962
    },
    "player": {
      "away": {
        "playerList": [
          {
            "appearanceCnt": 35,
            "assistAvgCnt": "0",
            "assistCnt": 1,
            "assistProbability": "3%",
            "goalAvgCnt": "0.6",
            "goalCnt": 22,
            "goalProbability": "44%",
            "injuryFlag": 0,
            "personId": 649618,
            "personName": "蒂亚戈",
            "playerPositionCode": "Forward",
            "playerPositionDesc": "前锋",
            "startedMatchCnt": 34,
            "substituteMatchCnt": 1,
            "suspensionFlag": 0,
            "uniformNo": "9"
          },
          {
            "appearanceCnt": 32,
            "assistAvgCnt": "0.1",
            "assistCnt": 3,
            "assistProbability": "9%",
            "goalAvgCnt": "0.2",
            "goalCnt": 7,
            "goalProbability": "14%",
            "injuryFlag": 0,
            "personId": 562536,
            "personName": "K. Schade",
            "playerPositionCode": "Midfielder",
            "playerPositionDesc": "中场",
            "startedMatchCnt": 30,
            "substituteMatchCnt": 2,
            "suspensionFlag": 0,
            "uniformNo": "7"
          },
          {
            "appearanceCnt": 29,
            "assistAvgCnt": "0.1",
            "assistCnt": 3,
            "assistProbability": "9%",
            "goalAvgCnt": "0.2",
            "goalCnt": 5,
            "goalProbability": "10%",
            "injuryFlag": 0,
            "personId": 671029,
            "personName": "D. Ouattara",
            "playerPositionCode": "Forward",
            "playerPositionDesc": "前锋",
            "startedMatchCnt": 23,
            "substituteMatchCnt": 6,
            "suspensionFlag": 0,
            "uniformNo": "19"
          }
        ],
        "sportteryTeamId": 69,
        "teamId": 722,
        "teamShortName": "布伦特",
        "uniformTeamId": 421
      },
      "home": {
        "playerList": [
          {
            "appearanceCnt": 33,
            "assistAvgCnt": "0.2",
            "assistCnt": 7,
            "assistProbability": "12%",
            "goalAvgCnt": "0.8",
            "goalCnt": 25,
            "goalProbability": "32%",
            "injuryFlag": 0,
            "personId": 441484,
            "personName": "E. Håland",
            "playerPositionCode": "Forward",
            "playerPositionDesc": "前锋",
            "startedMatchCnt": 32,
            "substituteMatchCnt": 1,
            "suspensionFlag": 0,
            "uniformNo": "9"
          },
          {
            "appearanceCnt": 33,
            "assistAvgCnt": "0.1",
            "assistCnt": 4,
            "assistProbability": "7%",
            "goalAvgCnt": "0.5",
            "goalCnt": 15,
            "goalProbability": "19%",
            "injuryFlag": 0,
            "personId": 529560,
            "personName": "塞梅尼奥",
            "playerPositionCode": "Forward",
            "playerPositionDesc": "前锋",
            "startedMatchCnt": 33,
            "substituteMatchCnt": 0,
            "suspensionFlag": 0,
            "uniformNo": "42"
          },
          {
            "appearanceCnt": 29,
            "assistAvgCnt": "0.1",
            "assistCnt": 3,
            "assistProbability": "5%",
            "goalAvgCnt": "0.2",
            "goalCnt": 7,
            "goalProbability": "9%",
            "injuryFlag": 0,
            "personId": 453102,
            "personName": "福登",
            "playerPositionCode": "Midfielder",
            "playerPositionDesc": "中场",
            "startedMatchCnt": 21,
            "substituteMatchCnt": 8,
            "suspensionFlag": 0,
            "uniformNo": "47"
          }
        ],
        "sportteryTeamId": 12,
        "teamId": 676,
        "teamShortName": "曼城",
        "uniformTeamId": 217
      },
      "seasonId": 13343,
      "seasonName": "2025/2026",
      "tournamentId": 127,
      "tournamentShortName": "英超",
      "uniformLeagueId": 72,
      "uniformMatchId": 2390962
    }
  },
  "ttg_change": {
    "6球": {
      "count": 1,
      "change_pct": 5.6
    },
    "4球": {
      "count": 1,
      "change_pct": -3.6
    },
    "1球": {
      "count": 0,
      "change_pct": 0.0
    },
    "0球": {
      "count": 0,
      "change_pct": 0.0
    },
    "5球": {
      "count": 0,
      "change_pct": 0.0
    },
    "7球": {
      "count": 1,
      "change_pct": 4.5
    },
    "2球": {
      "count": 1,
      "change_pct": 2.1
    },
    "3球": {
      "count": 1,
      "change_pct": -2.8
    }
  },
  "hafu_change": {
    "平负": {
      "count": 0,
      "change_pct": 0.0
    },
    "负平": {
      "count": 0,
      "change_pct": 0.0
    },
    "胜平": {
      "count": 0,
      "change_pct": 0.0
    },
    "胜负": {
      "count": 0,
      "change_pct": 0.0
    },
    "平平": {
      "count": 1,
      "change_pct": 5.6
    },
    "胜胜": {
      "count": 1,
      "change_pct": -2.3
    },
    "负胜": {
      "count": 0,
      "change_pct": 0.0
    },
    "负负": {
      "count": 1,
      "change_pct": 4.2
    },
    "平胜": {
      "count": 1,
      "change_pct": 1.2
    }
  },
  "had_change": {
    "胜": {
      "count": 3,
      "change_pct": -1.6
    },
    "负": {
      "count": 3,
      "change_pct": 4.9
    },
    "平": {
      "count": 3,
      "change_pct": 3.8
    }
  },
  "hhad_change": {
    "让胜": {
      "count": 3,
      "change_pct": -1.1
    },
    "让负": {
      "count": 3,
      "change_pct": 1.6
    },
    "让平": {
      "count": 0,
      "change_pct": 0.0
    }
  },
  "exclusion_list": [
    {
      "goal": "2球",
      "ttg_odds": "4.90",
      "ttg_special": false,
      "scores": [
        {
          "score": "02:00",
          "odds": "7.75",
          "special": true
        },
        {
          "score": "00:02",
          "odds": "55.00",
          "special": false
        },
        {
          "score": "01:01",
          "odds": "11.00",
          "special": false
        }
      ],
      "level": "仅比分排除",
      "reason": "进球数赔率4.90（普通），但对应比分中存在特殊尾数赔率，可优先排除特殊尾数比分"
    }
  ],
  "over_under": {
    "over_odds": 0.87,
    "ou_line": 3.5,
    "under_odds": 0.83,
    "save_time": "2026-05-09 21:12"
  }
}